CRPS/CRPS.py
CRPS/__init__.py
CRPS-2.0.4.dist-info/LICENSE
CRPS-2.0.4.dist-info/METADATA
CRPS-2.0.4.dist-info/WHEEL
CRPS-2.0.4.dist-info/top_level.txt
CRPS-2.0.4.dist-info/RECORD
