Metadata-Version: 2.1
Name: CRPS
Version: 2.0.4
Summary: A package to compute the Continuous Ranked Probability Score (CRPS), the Fair-CRPS, and the Adjusted-CRPS. Read the documentation at https://github.com/gouthamnaveen/CRPS
Home-page: https://github.com/gouthamnaveen/CRPS
Author: Naveen Goutham
Author-email: naveen.goutham@outlook.com
License: Apache License 2.0
Keywords: crps,continuous ranked probability score,fair crps,adjusted crps,proper score,probability score,ensemble forecast,python
Platform: UNKNOWN
License-File: LICENSE
Requires-Dist: numpy
